solidfire/__init__.py
solidfire/factory.py
solidfire/models.py
solidfire/adaptor/__init__.py
solidfire/adaptor/schedule_adaptor.py
solidfire/apiactual/__init__.py
solidfire/common/__init__.py
solidfire/common/model.py
solidfire/custom/__init__.py
solidfire/custom/models.py
solidfire/util/__init__.py
solidfire_sdk_python-12.3.0.203.dist-info/DESCRIPTION.rst
solidfire_sdk_python-12.3.0.203.dist-info/METADATA
solidfire_sdk_python-12.3.0.203.dist-info/RECORD
solidfire_sdk_python-12.3.0.203.dist-info/WHEEL
solidfire_sdk_python-12.3.0.203.dist-info/metadata.json
solidfire_sdk_python-12.3.0.203.dist-info/top_level.txt
