Metadata-Version: 2.0
Name: solidfire-sdk-python
Version: 12.3.0.203
Summary: SolidFire Python SDK
Home-page: UNKNOWN
Author: UNKNOWN
Author-email: UNKNOWN
License: Apache2
Keywords: solidfire nas iscsi fibre channel storage api sdk
Platform: UNKNOWN
Classifier: Development Status :: 5 - Production/Stable
Classifier: Operating System :: OS Independent
Classifier: Intended Audience :: Developers
Classifier: Intended Audience :: Information Technology
Classifier: Intended Audience :: System Administrators
Classifier: Topic :: Utilities
Classifier: Topic :: System :: Systems Administration
Classifier: Topic :: Software Development :: Libraries :: Application Frameworks
Classifier: License :: OSI Approved :: Apache Software License
Classifier: Programming Language :: Python :: 2
Classifier: Programming Language :: Python :: 2.7
Classifier: Programming Language :: Python :: 3
Classifier: Programming Language :: Python :: 3.3
Classifier: Programming Language :: Python :: 3.4
Classifier: Programming Language :: Python :: 3.5
Requires-Dist: enum34 (>=1.1.6)
Requires-Dist: future (>=0.15.2)
Requires-Dist: requests (>=2.9.1)
Requires-Dist: setuptools (>=19.2)
Provides-Extra: dev
Requires-Dist: check-manifest; extra == 'dev'
Provides-Extra: docs
Requires-Dist: Sphinx (>=1.3.5); extra == 'docs'
Requires-Dist: sphinx-rtd-theme (>=0.1.9); extra == 'docs'
Provides-Extra: release
Requires-Dist: twine (>=1.6.5); extra == 'release'
Provides-Extra: test
Requires-Dist: coverage; extra == 'test'
Requires-Dist: pyhamcrest (>=1.8.5); extra == 'test'
Requires-Dist: pytest (>=2.8.7); extra == 'test'
Requires-Dist: pytest-flake8 (>=0.1); extra == 'test'
